{
  "pacientes": [
    {
      "id": 1,
      "nome": "Fredo",
      "raca": "Maltes",
      "sexo": "M",
      "especie": "cachorro",
      "data": "07/04/2019",
      "peso": "10"
    },
    {
      "nome": "teste",
      "data": "25/02/2022",
      "peso": "10",
      "raca": "humano",
      "sexo": "M",
      "especie": "verde",
      "id": 2
    },
    {
      "nome": "teste2",
      "data": "25/02/2022",
      "peso": "10",
      "raca": "humano",
      "sexo": "M",
      "especie": "verde",
      "id": 3
    },
    {
      "nome": "teste22",
      "data": "25/02/2022",
      "peso": "10",
      "raca": "humano",
      "sexo": "M",
      "especie": "verde",
      "id": 4
    },
    {
      "nome": "teste221",
      "data": "25/02/2022",
      "peso": "10",
      "raca": "humano",
      "sexo": "M",
      "especie": "verde",
      "id": 5
    },
    {
      "nome": "teste2214",
      "data": "25/02/2022",
      "peso": "10",
      "raca": "humano",
      "sexo": "M",
      "especie": "verde",
      "id": 6
    },
    {
      "nome": "teste22145",
      "data": "25/02/2022",
      "peso": "10",
      "raca": "humano",
      "sexo": "M",
      "especie": "verde",
      "id": 7
    }
  ]
}